sage_templater/__init__.py
sage_templater/cli.py
sage_templater/clients.py
sage_templater/exceptions.py
sage_templater/plugin_manager.py
sage_templater/plugins/__init__.py
sage_templater/plugins/adapters/__init__.py
sage_templater/plugins/adapters/petit_cash_adapters.py
sage_templater/plugins/file_classifiers/__init__.py
sage_templater/plugins/file_classifiers/csv_classifiers.py
sage_templater/plugins/file_classifiers/excel_classifier.py
sage_templater/plugins/parsers/__init__.py
sage_templater/plugins/parsers/check_excel_parsers.py
sage_templater/plugins/parsers/date_parsers.py
sage_templater/plugins/parsers/excel_parser.py
sage_templater/plugins/parsers/petit_cash_excel_parsers.py
sage_templater/sage_templater.py
sage_templater/schemas.py
sage_templater/zip_utils.py
sage_templater-0.5.2.dist-info/LICENSE
sage_templater-0.5.2.dist-info/METADATA
sage_templater-0.5.2.dist-info/WHEEL
sage_templater-0.5.2.dist-info/entry_points.txt
sage_templater-0.5.2.dist-info/RECORD
