Metadata-Version: 2.1
Name: sage-templater
Version: 0.5.2
Summary: App to parse templates and create them as a Sage import files..
Home-page: https://github.com/luiscberrocal/sage-templater
License: MIT
Author: Luis C. Berrocal
Author-email: luis.berrocal.1942@gmail.com
Requires-Python: >=3.10,<3.13
Classifier: Development Status :: 2 - Pre-Alpha
Classifier: Intended Audience :: Developers
Classifier: License :: OSI Approved :: MIT License
Classifier: Natural Language :: English
Classifier: Programming Language :: Python :: 3
Classifier: Programming Language :: Python :: 3.10
Classifier: Programming Language :: Python :: 3.11
Classifier: Programming Language :: Python :: 3.12
Requires-Dist: click (>=8.1.7,<9.0.0)
Requires-Dist: openpyxl (>=3.1.5,<4.0.0)
Requires-Dist: pandas (>=2.2.3,<3.0.0)
Requires-Dist: pluggy (>=1.5.0,<2.0.0)
Requires-Dist: pydantic (>=2.9.2,<3.0.0)
Requires-Dist: rich (>=13.9.1,<14.0.0)
Requires-Dist: twine (>=5.1.1,<6.0.0)
Requires-Dist: xlrd (>=2.0.1,<3.0.0)
